chevron_blue/__init__.py
chevron_blue/main.py
chevron_blue/metadata.py
chevron_blue/renderer.py
chevron_blue/tokenizer.py
chevron_blue-0.3.0.dist-info/WHEEL
chevron_blue-0.3.0.dist-info/entry_points.txt
chevron_blue-0.3.0.dist-info/METADATA
chevron_blue-0.3.0.dist-info/RECORD
