Metadata-Version: 2.4
Name: chevron-blue
Version: 0.3.0
Summary: A Python implementation of the mustache template language
Author: Zanie Blue
Author-email: Zanie Blue <contact@zanie.dev>
License-Expression: MIT
Requires-Python: >=3.8
